Workbook

Sheet Instrucciones
B2: ARGOS INSIGHTS
B3: Plantilla de Orden Financiero
B4: Para tener tus facturas, tu flujo de caja y el ciclo OC-HES-EDP-Factura ordenados y fáciles de leer, en un solo Excel.
B6: Cómo usarla
B7: Celdas amarillas | C7: son las únicas que debes llenar tú. Todo lo demás se calcula solo.
B8: Celdas blancas | C8: se calculan automáticamente con fórmulas — no las edites, o se rompe el cálculo.
B9: Filas de ejemplo | C9: cada hoja trae 2-4 filas con datos de ejemplo (en gris) para que veas el formato. Bórralas o sobrescríbelas cuando cargues tus datos reales.
B10: Fechas | C10: escríbelas siempre como fecha (ej. 15-07-2026), no como texto, para que las fórmulas de atraso funcionen.
B12: Qué contiene cada hoja
B13: Resumen | C13: Vista rápida: cuánto te deben, tu plazo promedio y cuántas facturas están vencidas — sin tener que leer el resto.
B14: Cuentas por Cobrar | C14: Cada factura emitida, a quién, por cuánto, cuándo debería pagarse y su estado (pendiente / vencida / pagada).
B15: Flujo de Caja | C15: Proyección mes a mes de cuánta plata entra y sale, y el saldo que te va quedando.
B16: Ciclo Documental | C16: Seguimiento de cada venta desde la Orden de Compra hasta el pago (OC → HES → EDP → Factura → Pago).
B19: ¿Prefieres que esto viva en un dashboard en vez de un Excel? Eso es exactamente lo que hacemos en Argos Insights.
B20: argosinsights.org · argosconsulta@gmail.com · @argosinsights

Sheet Resumen
A1: Resumen Financiero
A2: Se actualiza solo a partir de las hojas Cuentas por Cobrar y Flujo de Caja.
B4: Total por Cobrar | C4: Plazo Promedio (días) | D4: Facturas Vencidas | E4: Saldo Proy. (últ. mes)
B5: =SUMIF('Cuentas por Cobrar'!H4:H28,"Pendiente",'Cuentas por Cobrar'!C4:C28)+SUMIF('Cuentas por Cobrar'!H4:H28,"Vencida",'Cuentas por Cobrar'!C4:C28) -> 6150000 | C5: =IFERROR(AVERAGEIFS('Cuentas por Cobrar'!E4:E28,'Cuentas por Cobrar'!A4:A28,"<>"),0) -> 45 | D5: =COUNTIF('Cuentas por Cobrar'!H4:H28,"Vencida") -> 0 | E5: ='Flujo de Caja'!G9 -> 12800000
B8: Estos cuatro números son los que un dashboard de Argos Insights mantiene siempre al día, sin que tengas que revisar ninguna planilla.

Sheet Cuentas por Cobrar
A1: Cuentas por Cobrar
A2: Llena las columnas amarillas (A-E y G si ya te pagaron). El resto se calcula solo.
A3: Cliente | B3: N° Factura | C3: Monto ($) | D3: Fecha Emisión | E3: Plazo (días) | F3: Fecha Estimada de Pago | G3: Fecha Real de Pago | H3: Estado | I3: Días de Atraso
A4: Constructora ABC (ejemplo) | B4: F-1042 | C4: 4200000 | D4: 46183 | E4: 45 | F4: =IF(AND(D4<>"",E4<>""),D4+E4,"") -> 46228 | H4: =IF(C4="","",IF(G4<>"","Pagada",IF(AND(F4<>"",TODAY()>F4),"Vencida","Pendiente"))) -> Pendiente | I4: =IF(H4="Vencida",TODAY()-F4,IF(AND(H4="Pagada",G4>F4),G4-F4,IF(H4="","",0))) -> 0
A5: Minera Sur (ejemplo) | B5: F-1043 | C5: 6800000 | D5: 46193 | E5: 60 | F5: =IF(AND(D5<>"",E5<>""),D5+E5,"") -> 46253 | G5: 46252 | H5: =IF(C5="","",IF(G5<>"","Pagada",IF(AND(F5<>"",TODAY()>F5),"Vencida","Pendiente"))) -> Pagada | I5: =IF(H5="Vencida",TODAY()-F5,IF(AND(H5="Pagada",G5>F5),G5-F5,IF(H5="","",0))) -> 0
A6: Retail Norte (ejemplo) | B6: F-1044 | C6: 1950000 | D6: 46204 | E6: 30 | F6: =IF(AND(D6<>"",E6<>""),D6+E6,"") -> 46234 | H6: =IF(C6="","",IF(G6<>"","Pagada",IF(AND(F6<>"",TODAY()>F6),"Vencida","Pendiente"))) -> Pendiente | I6: =IF(H6="Vencida",TODAY()-F6,IF(AND(H6="Pagada",G6>F6),G6-F6,IF(H6="","",0))) -> 0
F7: =IF(AND(D7<>"",E7<>""),D7+E7,"") | H7: =IF(C7="","",IF(G7<>"","Pagada",IF(AND(F7<>"",TODAY()>F7),"Vencida","Pendiente"))) | I7: =IF(H7="Vencida",TODAY()-F7,IF(AND(H7="Pagada",G7>F7),G7-F7,IF(H7="","",0)))
F8: =IF(AND(D8<>"",E8<>""),D8+E8,"") | H8: =IF(C8="","",IF(G8<>"","Pagada",IF(AND(F8<>"",TODAY()>F8),"Vencida","Pendiente"))) | I8: =IF(H8="Vencida",TODAY()-F8,IF(AND(H8="Pagada",G8>F8),G8-F8,IF(H8="","",0)))
F9: =IF(AND(D9<>"",E9<>""),D9+E9,"") | H9: =IF(C9="","",IF(G9<>"","Pagada",IF(AND(F9<>"",TODAY()>F9),"Vencida","Pendiente"))) | I9: =IF(H9="Vencida",TODAY()-F9,IF(AND(H9="Pagada",G9>F9),G9-F9,IF(H9="","",0)))
F10: =IF(AND(D10<>"",E10<>""),D10+E10,"") | H10: =IF(C10="","",IF(G10<>"","Pagada",IF(AND(F10<>"",TODAY()>F10),"Vencida","Pendiente"))) | I10: =IF(H10="Vencida",TODAY()-F10,IF(AND(H10="Pagada",G10>F10),G10-F10,IF(H10="","",0)))
F11: =IF(AND(D11<>"",E11<>""),D11+E11,"") | H11: =IF(C11="","",IF(G11<>"","Pagada",IF(AND(F11<>"",TODAY()>F11),"Vencida","Pendiente"))) | I11: =IF(H11="Vencida",TODAY()-F11,IF(AND(H11="Pagada",G11>F11),G11-F11,IF(H11="","",0)))
F12: =IF(AND(D12<>"",E12<>""),D12+E12,"") | H12: =IF(C12="","",IF(G12<>"","Pagada",IF(AND(F12<>"",TODAY()>F12),"Vencida","Pendiente"))) | I12: =IF(H12="Vencida",TODAY()-F12,IF(AND(H12="Pagada",G12>F12),G12-F12,IF(H12="","",0)))
F13: =IF(AND(D13<>"",E13<>""),D13+E13,"") | H13: =IF(C13="","",IF(G13<>"","Pagada",IF(AND(F13<>"",TODAY()>F13),"Vencida","Pendiente"))) | I13: =IF(H13="Vencida",TODAY()-F13,IF(AND(H13="Pagada",G13>F13),G13-F13,IF(H13="","",0)))
F14: =IF(AND(D14<>"",E14<>""),D14+E14,"") | H14: =IF(C14="","",IF(G14<>"","Pagada",IF(AND(F14<>"",TODAY()>F14),"Vencida","Pendiente"))) | I14: =IF(H14="Vencida",TODAY()-F14,IF(AND(H14="Pagada",G14>F14),G14-F14,IF(H14="","",0)))
F15: =IF(AND(D15<>"",E15<>""),D15+E15,"") | H15: =IF(C15="","",IF(G15<>"","Pagada",IF(AND(F15<>"",TODAY()>F15),"Vencida","Pendiente"))) | I15: =IF(H15="Vencida",TODAY()-F15,IF(AND(H15="Pagada",G15>F15),G15-F15,IF(H15="","",0)))
F16: =IF(AND(D16<>"",E16<>""),D16+E16,"") | H16: =IF(C16="","",IF(G16<>"","Pagada",IF(AND(F16<>"",TODAY()>F16),"Vencida","Pendiente"))) | I16: =IF(H16="Vencida",TODAY()-F16,IF(AND(H16="Pagada",G16>F16),G16-F16,IF(H16="","",0)))
F17: =IF(AND(D17<>"",E17<>""),D17+E17,"") | H17: =IF(C17="","",IF(G17<>"","Pagada",IF(AND(F17<>"",TODAY()>F17),"Vencida","Pendiente"))) | I17: =IF(H17="Vencida",TODAY()-F17,IF(AND(H17="Pagada",G17>F17),G17-F17,IF(H17="","",0)))
F18: =IF(AND(D18<>"",E18<>""),D18+E18,"") | H18: =IF(C18="","",IF(G18<>"","Pagada",IF(AND(F18<>"",TODAY()>F18),"Vencida","Pendiente"))) | I18: =IF(H18="Vencida",TODAY()-F18,IF(AND(H18="Pagada",G18>F18),G18-F18,IF(H18="","",0)))
... F28: =IF(AND(D28<>"",E28<>""),D28+E28,"") | H28: =IF(C28="","",IF(G28<>"","Pagada",IF(AND(F28<>"",TODAY()>F28),"Vencida","Pendiente"))) | I28: =IF(H28="Vencida",TODAY()-F28,IF(AND(H28="Pagada",G28>F28),G28-F28,IF(H28="","",0)))

Sheet Flujo de Caja
A1: Flujo de Caja Proyectado
A2: Llena el saldo inicial del primer mes y tus egresos estimados. El saldo final se arrastra solo mes a mes.
A3: Mes | B3: Saldo Inicial | C3: Cobros Esperados* | D3: Otros Ingresos | E3: Egresos Fijos | F3: Egresos Variables | G3: Saldo Final
A4: 46235 | B4: 8000000 | C4: =SUMIFS('Cuentas por Cobrar'!$C$4:$C$28,'Cuentas por Cobrar'!$F$4:$F$28,">="&A4,'Cuentas por Cobrar'!$F$4:$F$28,"<"&EDATE(A4,1)) -> 6800000 | D4: 0 | E4: 1500000 | F4: 500000 | G4: =B4+C4+D4-E4-F4 -> 12800000
A5: 46266 | B5: =G4 -> 12800000 | C5: =SUMIFS('Cuentas por Cobrar'!$C$4:$C$28,'Cuentas por Cobrar'!$F$4:$F$28,">="&A5,'Cuentas por Cobrar'!$F$4:$F$28,"<"&EDATE(A5,1)) -> 0 | D5: 0 | E5: 0 | F5: 0 | G5: =B5+C5+D5-E5-F5 -> 12800000
A6: 46296 | B6: =G5 -> 12800000 | C6: =SUMIFS('Cuentas por Cobrar'!$C$4:$C$28,'Cuentas por Cobrar'!$F$4:$F$28,">="&A6,'Cuentas por Cobrar'!$F$4:$F$28,"<"&EDATE(A6,1)) -> 0 | D6: 0 | E6: 0 | F6: 0 | G6: =B6+C6+D6-E6-F6 -> 12800000
A7: 46327 | B7: =G6 -> 12800000 | C7: =SUMIFS('Cuentas por Cobrar'!$C$4:$C$28,'Cuentas por Cobrar'!$F$4:$F$28,">="&A7,'Cuentas por Cobrar'!$F$4:$F$28,"<"&EDATE(A7,1)) -> 0 | D7: 0 | E7: 0 | F7: 0 | G7: =B7+C7+D7-E7-F7 -> 12800000
A8: 46357 | B8: =G7 -> 12800000 | C8: =SUMIFS('Cuentas por Cobrar'!$C$4:$C$28,'Cuentas por Cobrar'!$F$4:$F$28,">="&A8,'Cuentas por Cobrar'!$F$4:$F$28,"<"&EDATE(A8,1)) -> 0 | D8: 0 | E8: 0 | F8: 0 | G8: =B8+C8+D8-E8-F8 -> 12800000
A9: 46388 | B9: =G8 -> 12800000 | C9: =SUMIFS('Cuentas por Cobrar'!$C$4:$C$28,'Cuentas por Cobrar'!$F$4:$F$28,">="&A9,'Cuentas por Cobrar'!$F$4:$F$28,"<"&EDATE(A9,1)) -> 0 | D9: 0 | E9: 0 | F9: 0 | G9: =B9+C9+D9-E9-F9 -> 12800000
A11: *Cobros Esperados se calcula solo, sumando las facturas de la hoja 'Cuentas por Cobrar' cuya Fecha Estimada de Pago cae en ese mes.

Sheet Ciclo Documental
A1: Ciclo Documental (OC → HES → EDP → Factura → Pago)
A2: Llena la fecha de cada etapa a medida que ocurre. La etapa actual y los días en el ciclo se calculan solos.
A3: Cliente | B3: N° OC | C3: Fecha OC | D3: Fecha HES | E3: Fecha EDP | F3: Fecha Factura | G3: Fecha Pago | H3: Etapa Actual | I3: Días en el Ciclo
A4: Constructora ABC (ejemplo) | B4: OC-3301 | C4: 46144 | D4: 46162 | E4: 46176 | F4: 46183 | H4: =IF(G4<>"","Pagado",IF(F4<>"","Facturado",IF(E4<>"","EDP Emitido",IF(D4<>"","HES Emitida",IF(C4<>"","OC Emitida","Sin iniciar"))))) -> Facturado | I4: =IF(C4="","",IF(G4<>"",G4-C4,TODAY()-C4)) -> 75
A5: Minera Sur (ejemplo) | B5: OC-3302 | C5: 46174 | D5: 46188 | H5: =IF(G5<>"","Pagado",IF(F5<>"","Facturado",IF(E5<>"","EDP Emitido",IF(D5<>"","HES Emitida",IF(C5<>"","OC Emitida","Sin iniciar"))))) -> HES Emitida | I5: =IF(C5="","",IF(G5<>"",G5-C5,TODAY()-C5)) -> 45
A6: Retail Norte (ejemplo) | B6: OC-3303 | C6: 46208 | H6: =IF(G6<>"","Pagado",IF(F6<>"","Facturado",IF(E6<>"","EDP Emitido",IF(D6<>"","HES Emitida",IF(C6<>"","OC Emitida","Sin iniciar"))))) -> OC Emitida | I6: =IF(C6="","",IF(G6<>"",G6-C6,TODAY()-C6)) -> 11
H7: =IF(G7<>"","Pagado",IF(F7<>"","Facturado",IF(E7<>"","EDP Emitido",IF(D7<>"","HES Emitida",IF(C7<>"","OC Emitida","Sin iniciar"))))) -> Sin iniciar | I7: =IF(C7="","",IF(G7<>"",G7-C7,TODAY()-C7))
H8: =IF(G8<>"","Pagado",IF(F8<>"","Facturado",IF(E8<>"","EDP Emitido",IF(D8<>"","HES Emitida",IF(C8<>"","OC Emitida","Sin iniciar"))))) -> Sin iniciar | I8: =IF(C8="","",IF(G8<>"",G8-C8,TODAY()-C8))
H9: =IF(G9<>"","Pagado",IF(F9<>"","Facturado",IF(E9<>"","EDP Emitido",IF(D9<>"","HES Emitida",IF(C9<>"","OC Emitida","Sin iniciar"))))) -> Sin iniciar | I9: =IF(C9="","",IF(G9<>"",G9-C9,TODAY()-C9))
H10: =IF(G10<>"","Pagado",IF(F10<>"","Facturado",IF(E10<>"","EDP Emitido",IF(D10<>"","HES Emitida",IF(C10<>"","OC Emitida","Sin iniciar"))))) -> Sin iniciar | I10: =IF(C10="","",IF(G10<>"",G10-C10,TODAY()-C10))
H11: =IF(G11<>"","Pagado",IF(F11<>"","Facturado",IF(E11<>"","EDP Emitido",IF(D11<>"","HES Emitida",IF(C11<>"","OC Emitida","Sin iniciar"))))) -> Sin iniciar | I11: =IF(C11="","",IF(G11<>"",G11-C11,TODAY()-C11))
H12: =IF(G12<>"","Pagado",IF(F12<>"","Facturado",IF(E12<>"","EDP Emitido",IF(D12<>"","HES Emitida",IF(C12<>"","OC Emitida","Sin iniciar"))))) -> Sin iniciar | I12: =IF(C12="","",IF(G12<>"",G12-C12,TODAY()-C12))
H13: =IF(G13<>"","Pagado",IF(F13<>"","Facturado",IF(E13<>"","EDP Emitido",IF(D13<>"","HES Emitida",IF(C13<>"","OC Emitida","Sin iniciar"))))) -> Sin iniciar | I13: =IF(C13="","",IF(G13<>"",G13-C13,TODAY()-C13))
H14: =IF(G14<>"","Pagado",IF(F14<>"","Facturado",IF(E14<>"","EDP Emitido",IF(D14<>"","HES Emitida",IF(C14<>"","OC Emitida","Sin iniciar"))))) -> Sin iniciar | I14: =IF(C14="","",IF(G14<>"",G14-C14,TODAY()-C14))
H15: =IF(G15<>"","Pagado",IF(F15<>"","Facturado",IF(E15<>"","EDP Emitido",IF(D15<>"","HES Emitida",IF(C15<>"","OC Emitida","Sin iniciar"))))) -> Sin iniciar | I15: =IF(C15="","",IF(G15<>"",G15-C15,TODAY()-C15))
H16: =IF(G16<>"","Pagado",IF(F16<>"","Facturado",IF(E16<>"","EDP Emitido",IF(D16<>"","HES Emitida",IF(C16<>"","OC Emitida","Sin iniciar"))))) -> Sin iniciar | I16: =IF(C16="","",IF(G16<>"",G16-C16,TODAY()-C16))
H17: =IF(G17<>"","Pagado",IF(F17<>"","Facturado",IF(E17<>"","EDP Emitido",IF(D17<>"","HES Emitida",IF(C17<>"","OC Emitida","Sin iniciar"))))) -> Sin iniciar | I17: =IF(C17="","",IF(G17<>"",G17-C17,TODAY()-C17))
H18: =IF(G18<>"","Pagado",IF(F18<>"","Facturado",IF(E18<>"","EDP Emitido",IF(D18<>"","HES Emitida",IF(C18<>"","OC Emitida","Sin iniciar"))))) -> Sin iniciar | I18: =IF(C18="","",IF(G18<>"",G18-C18,TODAY()-C18))
... H23: =IF(G23<>"","Pagado",IF(F23<>"","Facturado",IF(E23<>"","EDP Emitido",IF(D23<>"","HES Emitida",IF(C23<>"","OC Emitida","Sin iniciar"))))) -> Sin iniciar | I23: =IF(C23="","",IF(G23<>"",G23-C23,TODAY()-C23))
